pybelqis/__init__.py
pybelqis/clients.py
pybelqis-0.4.4.dist-info/LICENSE
pybelqis-0.4.4.dist-info/METADATA
pybelqis-0.4.4.dist-info/WHEEL
pybelqis-0.4.4.dist-info/top_level.txt
pybelqis-0.4.4.dist-info/RECORD
