Metadata-Version: 2.1
Name: pybelqis
Version: 0.4.4
Summary: A python client of Belqis systems. Allows you to query the services of Belqis systems from a python program
Author-email: Ahmed Khorsi <ahmedkhorsi18@gmail.com>
Project-URL: Homepage, https://github.com/ahmedkhorsi/pybelqis
Project-URL: Bug Tracker, https://github.com/ahmedkhorsi/pybelqis/issues
Classifier: Programming Language :: Python :: 3
Classifier: License :: OSI Approved :: MIT License
Classifier: Operating System :: OS Independent
Requires-Python: >=3.6
License-File: LICENSE
Requires-Dist: gql
Requires-Dist: aiohttp
